local_attention_tf/__init__.py
local_attention_tf/audio.py
local_attention_tf/blocks.py
local_attention_tf/image.py
local_attention_tf/layers.py
local_attention_tf/text.py
local_attention_tf-0.0.3.dist-info/METADATA
local_attention_tf-0.0.3.dist-info/WHEEL
local_attention_tf-0.0.3.dist-info/top_level.txt
local_attention_tf-0.0.3.dist-info/RECORD
