Metadata-Version: 2.1
Name: local-attention-tf
Version: 0.0.3
Summary: Local attention, window with lookback, for Image, Audio and language modeling
Home-page: https://github.com/anas-rz/local-attention-tf
Author: Muhammad Anas Raza
Author-email: memanasraza@gmail.com
License: MIT
Keywords: transformers,attention,artificial intelligence
Classifier: Development Status :: 4 - Beta
Classifier: Intended Audience :: Developers
Classifier: Topic :: Scientific/Engineering :: Artificial Intelligence
Classifier: License :: OSI Approved :: MIT License
Classifier: Programming Language :: Python :: 3.6
Requires-Dist: einops (>=0.6.0)
Requires-Dist: tensorflow
